zs_selenium_youtube/__init__.py
zs_selenium_youtube/youtube.py
zs_selenium_youtube/enums/__init__.py
zs_selenium_youtube/enums/analytics_period.py
zs_selenium_youtube/enums/analytics_tab.py
zs_selenium_youtube/enums/upload_status.py
zs_selenium_youtube/enums/visibility.py
zs_selenium_youtube-2.0.20.dist-info/LICENSE
zs_selenium_youtube-2.0.20.dist-info/METADATA
zs_selenium_youtube-2.0.20.dist-info/WHEEL
zs_selenium_youtube-2.0.20.dist-info/top_level.txt
zs_selenium_youtube-2.0.20.dist-info/RECORD
