Metadata-Version: 2.1
Name: zs-selenium-youtube
Version: 2.0.20
Summary: zs_selenium_youtube
Home-page: https://github.com/Zselter07/selenium_youtube
Author: Zselter
License: UNKNOWN
Platform: UNKNOWN
Classifier: Programming Language :: Python :: 3
Classifier: License :: OSI Approved :: MIT License
Classifier: Operating System :: OS Independent
Requires-Python: >=3.5
Requires-Dist: selenium-firefox
Requires-Dist: selenium-uploader-account
Requires-Dist: kcu
Requires-Dist: selenium
Requires-Dist: kstopit
Requires-Dist: noraise
Requires-Dist: kyoutubescraper
Requires-Dist: beautifulsoup4
